scale_gp/__init__.py
scale_gp/_base_client.py
scale_gp/_client.py
scale_gp/_compat.py
scale_gp/_constants.py
scale_gp/_exceptions.py
scale_gp/_files.py
scale_gp/_models.py
scale_gp/_qs.py
scale_gp/_resource.py
scale_gp/_response.py
scale_gp/_streaming.py
scale_gp/_types.py
scale_gp/_version.py
scale_gp/pagination.py
scale_gp/py.typed
scale_gp/_utils/__init__.py
scale_gp/_utils/_logs.py
scale_gp/_utils/_parsing.py
scale_gp/_utils/_proxy.py
scale_gp/_utils/_reflection.py
scale_gp/_utils/_streams.py
scale_gp/_utils/_sync.py
scale_gp/_utils/_transform.py
scale_gp/_utils/_typing.py
scale_gp/_utils/_utils.py
scale_gp/lib/__init__.py
scale_gp/lib/application_builder.py
scale_gp/lib/dataset_builder.py
scale_gp/lib/external_applications.py
scale_gp/lib/types/__init__.py
scale_gp/lib/types/data_locator.py
scale_gp/lib/types/multiturn.py
scale_gp/lib/types/summarization.py
scale_gp/lib/types/translation.py
scale_gp/resources/__init__.py
scale_gp/resources/accounts.py
scale_gp/resources/agents.py
scale_gp/resources/alias.py
scale_gp/resources/application_deployments.py
scale_gp/resources/application_schemas.py
scale_gp/resources/application_specs.py
scale_gp/resources/application_test_case_outputs.py
scale_gp/resources/application_threads.py
scale_gp/resources/application_variant_reports.py
scale_gp/resources/application_variants.py
scale_gp/resources/chat_completions.py
scale_gp/resources/chunks.py
scale_gp/resources/completions.py
scale_gp/resources/deployment_packages.py
scale_gp/resources/evaluation_configs.py
scale_gp/resources/interactions.py
scale_gp/resources/knowledge_base_data_sources.py
scale_gp/resources/model_templates.py
scale_gp/resources/question_sets.py
scale_gp/resources/questions.py
scale_gp/resources/studio_projects.py
scale_gp/resources/themes.py
scale_gp/resources/users.py
scale_gp/resources/applications/__init__.py
scale_gp/resources/applications/applications.py
scale_gp/resources/applications/dashboards.py
scale_gp-0.1.0a59.dist-info/METADATA
scale_gp-0.1.0a59.dist-info/WHEEL
scale_gp-0.1.0a59.dist-info/licenses/LICENSE
scale_gp-0.1.0a59.dist-info/RECORD
